JTranslator.py
setup.py
JTranslator.egg-info/PKG-INFO
JTranslator.egg-info/SOURCES.txt
JTranslator.egg-info/dependency_links.txt
JTranslator.egg-info/requires.txt
JTranslator.egg-info/top_level.txt