Metadata-Version: 1.1
Name: JTranslator
Version: 0.1
Summary: Translate texts with python
Home-page: https://twitter.com/joaok63
Author: João Mário
Author-email: joaok63@outlook.com
License: UNKNOWN
Keywords: Translate Translator
Platform: UNKNOWN
Classifier: Development Status :: 3 - Alpha
Classifier: Environment :: Console
Classifier: Programming Language :: Python :: 3
Classifier: Programming Language :: Python :: 3.3
Classifier: Programming Language :: Python :: 3.4
Classifier: Programming Language :: Python :: 3.5
